hathaway_analytics/__init__.py
hathaway_analytics/core.py
hathaway_analytics-0.1.0.dist-info/LICENSE
hathaway_analytics-0.1.0.dist-info/METADATA
hathaway_analytics-0.1.0.dist-info/WHEEL
hathaway_analytics-0.1.0.dist-info/top_level.txt
hathaway_analytics-0.1.0.dist-info/RECORD
